lenlab/__init__.py
lenlab/__main__.py
lenlab/datasheet.md
lenlab/datenblatt.md
lenlab/language.py
lenlab/lenlab_fw.bin
lenlab/message.py
lenlab/queued.py
lenlab/spy.py
lenlab/translate.py
lenlab/app/__init__.py
lenlab/app/about.py
lenlab/app/bode.py
lenlab/app/chart.py
lenlab/app/checkbox.py
lenlab/app/figure.py
lenlab/app/main.py
lenlab/app/oscilloscope.py
lenlab/app/poster.py
lenlab/app/programmer.py
lenlab/app/save_as.py
lenlab/app/signal.py
lenlab/app/symbols.py
lenlab/app/voltmeter.py
lenlab/app/window.py
lenlab/controller/__init__.py
lenlab/controller/auto_save.py
lenlab/controller/csv.py
lenlab/controller/image.py
lenlab/controller/lenlab.py
lenlab/controller/programmer.py
lenlab/controller/report.py
lenlab/controller/signal.py
lenlab/launchpad/__init__.py
lenlab/launchpad/bsl.py
lenlab/launchpad/discovery.py
lenlab/launchpad/launchpad.py
lenlab/launchpad/port_info.py
lenlab/launchpad/protocol.py
lenlab/launchpad/rules.py
lenlab/launchpad/terminal.py
lenlab/model/__init__.py
lenlab/model/chart.py
lenlab/model/points.py
lenlab/model/waveform.py
lenlab-8.6.1.dist-info/METADATA
lenlab-8.6.1.dist-info/WHEEL
lenlab-8.6.1.dist-info/entry_points.txt
lenlab-8.6.1.dist-info/licenses/LICENSE
lenlab-8.6.1.dist-info/RECORD
