Metadata-Version: 2.4
Name: lenlab
Version: 8.6.1
Dynamic: Summary
Project-URL: Home, https://github.com/kalanzun/lenlab_mspm0
Author-email: Christoph Simon <christoph.simon@kit.edu>
License:                                  Apache License
License-File: LICENSE
Classifier: License :: OSI Approved :: Apache Software License
Requires-Python: >=3.12
Requires-Dist: attrs>=24.3.0
Requires-Dist: matplotlib>=3.9.2
Requires-Dist: numpy>=2.1.3
Requires-Dist: pyside6>=6.7
